searchlight/__init__.py
searchlight/context.py
searchlight/gateway.py
searchlight/i18n.py
searchlight/listener.py
searchlight/notifier.py
searchlight/opts.py
searchlight/pipeline.py
searchlight/plugin.py
searchlight/service.py
searchlight/service_policies.py
searchlight/version.py
searchlight/api/__init__.py
searchlight/api/common.py
searchlight/api/policy.py
searchlight/api/property_protections.py
searchlight/api/versions.py
searchlight/api/wsgi.py
searchlight/api/middleware/__init__.py
searchlight/api/middleware/context.py
searchlight/api/middleware/gzip.py
searchlight/api/middleware/version_negotiation.py
searchlight/api/v1/__init__.py
searchlight/api/v1/router.py
searchlight/api/v1/search.py
searchlight/cmd/__init__.py
searchlight/cmd/api.py
searchlight/cmd/control.py
searchlight/cmd/listener.py
searchlight/cmd/manage.py
searchlight/cmd/status.py
searchlight/common/__init__.py
searchlight/common/config.py
searchlight/common/exception.py
searchlight/common/loggers.py
searchlight/common/property_utils.py
searchlight/common/resource_types.py
searchlight/common/utils.py
searchlight/common/wsgi.py
searchlight/common/wsme_utils.py
searchlight/common/policies/__init__.py
searchlight/common/policies/base.py
searchlight/common/policies/resource.py
searchlight/common/policies/search.py
searchlight/elasticsearch/__init__.py
searchlight/elasticsearch/plugins/__init__.py
searchlight/elasticsearch/plugins/base.py
searchlight/elasticsearch/plugins/helper.py
searchlight/elasticsearch/plugins/openstack_clients.py
searchlight/elasticsearch/plugins/utils.py
searchlight/elasticsearch/plugins/cinder/__init__.py
searchlight/elasticsearch/plugins/cinder/snapshots.py
searchlight/elasticsearch/plugins/cinder/snapshots_notification_handler.py
searchlight/elasticsearch/plugins/cinder/volumes.py
searchlight/elasticsearch/plugins/cinder/volumes_notification_handler.py
searchlight/elasticsearch/plugins/designate/__init__.py
searchlight-9.0.0.dist-info/DESCRIPTION.rst
searchlight-9.0.0.dist-info/METADATA
searchlight-9.0.0.dist-info/RECORD
searchlight-9.0.0.dist-info/WHEEL
searchlight-9.0.0.dist-info/entry_points.txt
searchlight-9.0.0.dist-info/metadata.json
searchlight-9.0.0.dist-info/pbr.json
searchlight-9.0.0.dist-info/top_level.txt
