Metadata-Version: 2.0
Name: searchlight
Version: 9.0.0
Summary: OpenStack Search Service
Home-page: https://docs.openstack.org/searchlight/latest/
Author: OpenStack
Author-email: openstack-discuss@lists.openstack.org
License: UNKNOWN
Platform: UNKNOWN
Classifier: Environment :: OpenStack
Classifier: Intended Audience :: Information Technology
Classifier: Intended Audience :: System Administrators
Classifier: License :: OSI Approved :: Apache Software License
Classifier: Operating System :: POSIX :: Linux
Classifier: Programming Language :: Python
Classifier: Programming Language :: Python :: Implementation :: CPython
Classifier: Programming Language :: Python :: 3 :: Only
Classifier: Programming Language :: Python :: 3
Classifier: Programming Language :: Python :: 3.6
Classifier: Programming Language :: Python :: 3.7
Requires-Python: >=3.6
Requires-Dist: Paste (>=2.0.2)
Requires-Dist: PasteDeploy (>=1.5.0)
Requires-Dist: Routes (>=2.3.1)
Requires-Dist: WSME (>=0.8.0)
Requires-Dist: WebOb (>=1.8.4)
Requires-Dist: elasticsearch (<3.0.0,>=2.0.0)
Requires-Dist: eventlet (!=0.18.3,!=0.20.1,>=0.18.2)
Requires-Dist: greenlet (>=0.4.10)
Requires-Dist: keystonemiddleware (>=4.17.0)
Requires-Dist: oslo.concurrency (>=3.26.0)
Requires-Dist: oslo.config (>=5.2.0)
Requires-Dist: oslo.context (>=2.19.2)
Requires-Dist: oslo.i18n (>=3.15.3)
Requires-Dist: oslo.log (>=3.36.0)
Requires-Dist: oslo.messaging (>=5.29.0)
Requires-Dist: oslo.middleware (>=3.31.0)
Requires-Dist: oslo.policy (>=1.30.0)
Requires-Dist: oslo.reports (>=1.18.0)
Requires-Dist: oslo.serialization (!=2.19.1,>=2.18.0)
Requires-Dist: oslo.service (>=1.33.0)
Requires-Dist: oslo.upgradecheck (>=0.1.0)
Requires-Dist: oslo.utils (>=3.33.0)
Requires-Dist: osprofiler (>=1.4.0)
Requires-Dist: pbr (!=2.1.0,>=2.0.0)
Requires-Dist: pyOpenSSL (>=17.1.0)
Requires-Dist: python-cinderclient (>=3.3.0)
Requires-Dist: python-designateclient (>=2.7.0)
Requires-Dist: python-glanceclient (>=2.8.0)
Requires-Dist: python-ironicclient (>=2.3.0)
Requires-Dist: python-keystoneclient (>=3.8.0)
Requires-Dist: python-neutronclient (>=6.11.0)
Requires-Dist: python-novaclient (>=9.1.0)
Requires-Dist: python-swiftclient (>=3.2.0)
Requires-Dist: stevedore (>=1.20.0)
